pfizer_components/Accordion.py
pfizer_components/Alert.py
pfizer_components/Badge.py
pfizer_components/Breadcrumb.py
pfizer_components/Button.py
pfizer_components/Card.py
pfizer_components/Cards.py
pfizer_components/Carousel.py
pfizer_components/Checkbox.py
pfizer_components/Dropdown.py
pfizer_components/Form.py
pfizer_components/Graph.py
pfizer_components/Input.py
pfizer_components/Label.py
pfizer_components/Modal.py
pfizer_components/Modals.py
pfizer_components/Nav.py
pfizer_components/Navigation.py
pfizer_components/RadioItems.py
pfizer_components/RangeSlider.py
pfizer_components/Slider.py
pfizer_components/Tab.py
pfizer_components/Toast.py
pfizer_components/Tooltip.py
pfizer_components/Usage_css.py
pfizer_components/Usage_python.py
pfizer_components/__init__.py
pfizer_components/assets/1.PNG
pfizer_components/assets/2.PNG
pfizer_components/assets/3.PNG
pfizer_components/assets/dbc.css
pfizer_components/assets/iconimage.svg
pfizer_components/assets/plus.svg
pfizer_components/assets/tick.svg
pfizer_components/run_components/Alert.py
pfizer_components/run_components/Badge.py
pfizer_components/run_components/Button.py
pfizer_components/run_components/Checkbox.py
pfizer_components/run_components/Dropdown.py
pfizer_components/run_components/Input.py
pfizer_components/run_components/Label.py
pfizer_components/run_components/RadioItems.py
pfizer_components/run_components/Slider.py
pfizer_components/run_components/Tab.py
pfizer_components/run_components/ToolTip.py
pfizer_components/run_components/__init__.py
pfizer_components/run_components/form.py
pfizer_components_new-0.2.6.dist-info/METADATA
pfizer_components_new-0.2.6.dist-info/WHEEL
pfizer_components_new-0.2.6.dist-info/top_level.txt
pfizer_components_new-0.2.6.dist-info/RECORD
