Metadata-Version: 2.1
Name: pfizer-components-new
Version: 0.2.6
Summary: Custom Python Dash Components for Pfizer.
Home-page: UNKNOWN
Author: ZS Associates
License: UNKNOWN
Platform: UNKNOWN
Classifier: Programming Language :: Python :: 3
Classifier: License :: OSI Approved :: MIT License
Classifier: Operating System :: OS Independent
Requires-Python: >=3.6
